{
  "name": "blank-machine",
  "machineType": "genericMachine",
  "vendorInfo" : { },
  "buildEnvironment": {
    "width": 500,
    "length": 500
  },
  "workEnvelope": {
      "shape": "rectangle",
      "width": 0,
      "length": 0,
      "position": {
        "x": 0,
        "y": 0,
        "z": 0
      }
  },
  "motors": [ ],
  "blocks": [ ],
  "tools": [
    {
      "name": "blankTool",
      "componentType": "Tool",
      "dimensions": {
          "width": 0,
          "height": 0,
          "length": 0
      },
      "toolType": "blankTool",
      "attributes": {
      }
    }
  ],
  "connections": [ ]
}
